MANIFEST.in
setup.py
opus20/__init__.py
opus20/fakeserver.py
opus20/opus20.py
opus20/opus20_cli.py
opus20/opus20_discovery.py
opus20/opus20_fakeserver.py
opus20/opus20_web.py
opus20.egg-info/PKG-INFO
opus20.egg-info/SOURCES.txt
opus20.egg-info/dependency_links.txt
opus20.egg-info/entry_points.txt
opus20.egg-info/requires.txt
opus20.egg-info/top_level.txt
opus20.egg-info/zip-safe
opus20/webapp/__init__.py
opus20/webapp/static/css/style.css
opus20/webapp/static/js/script.js
opus20/webapp/views/about.jinja2
opus20/webapp/views/base.jinja2
opus20/webapp/views/debug.jinja2
opus20/webapp/views/plots.jinja2
opus20/webapp/views/status.jinja2