Metadata-Version: 1.1
Name: opus20
Version: 1.0.1
Summary: Interface to Lufft OPUS20 devices
Home-page: UNKNOWN
Author: Philipp Klaus
Author-email: klaus@physik.uni-frankfurt.de
License: GPL
Keywords: Lufft Opus20
Platform: any
Classifier: Development Status :: 4 - Beta
Classifier: Operating System :: OS Independent
Classifier: License :: OSI Approved :: GNU General Public License v3 (GPLv3)
Classifier: Programming Language :: Python
Classifier: Programming Language :: Python :: 3
Classifier: Programming Language :: Python :: 3.3
Classifier: Topic :: System :: Monitoring
Classifier: Topic :: System :: Logging
